LICENSE
README.md
setup.py
src/zonefile_migrate/__init__.py
src/zonefile_migrate/__main__.py
src/zonefile_migrate/dns_record_set.py
src/zonefile_migrate/logger.py
src/zonefile_migrate/to_cloudformation.py
src/zonefile_migrate/to_terraform.py
src/zonefile_migrate/utils.py
src/zonefile_migrate.egg-info/PKG-INFO
src/zonefile_migrate.egg-info/SOURCES.txt
src/zonefile_migrate.egg-info/dependency_links.txt
src/zonefile_migrate.egg-info/entry_points.txt
src/zonefile_migrate.egg-info/not-zip-safe
src/zonefile_migrate.egg-info/requires.txt
src/zonefile_migrate.egg-info/top_level.txt
src/zonefile_migrate/terraform-modules/google-managed-zone.tf