Metadata-Version: 2.1
Name: zonefile-migrate
Version: 0.4.4
Summary: utility to migrate DNS managed zones 
Home-page: https://github.com/binxio/zonefile-migrate
Author: Mark van Holsteijn
Author-email: markvanholsteijn@binx.io
License: BSD
Platform: any
Classifier: Development Status :: 4 - Beta
Classifier: Environment :: Console
Classifier: Intended Audience :: Developers
Classifier: License :: OSI Approved :: BSD License
Classifier: Operating System :: POSIX
Classifier: Operating System :: MacOS
Classifier: Operating System :: Unix
Classifier: Operating System :: Microsoft :: Windows
Classifier: Programming Language :: Python
Classifier: Programming Language :: Python :: 3
Classifier: Topic :: Software Development :: Libraries :: Python Modules
License-File: LICENSE
